opencivicdata/__init__.py
opencivicdata/common.py
opencivicdata/divisions.py
opencivicdata/core/__init__.py
opencivicdata/core/apps.py
opencivicdata/core/admin/__init__.py
opencivicdata/core/admin/base.py
opencivicdata/core/admin/organization.py
opencivicdata/core/admin/other.py
opencivicdata/core/admin/person.py
opencivicdata/core/management/__init__.py
opencivicdata/core/management/commands/__init__.py
opencivicdata/core/management/commands/loaddivisions.py
opencivicdata/core/migrations/0001_initial.py
opencivicdata/core/migrations/0002_post_maximum_memberships.py
opencivicdata/core/migrations/0003_field_docs.py
opencivicdata/core/migrations/0004_auto_20171005_2028.py
opencivicdata/core/migrations/0005_auto_20191031_1507.py
opencivicdata/core/migrations/0005_auto_20191124_1658.py
opencivicdata/core/migrations/0006_merge_20200103_1432.py
opencivicdata/core/migrations/__init__.py
opencivicdata/core/models/__init__.py
opencivicdata/core/models/base.py
opencivicdata/core/models/division.py
opencivicdata/core/models/jurisdiction.py
opencivicdata/core/models/people_orgs.py
opencivicdata/elections/__init__.py
opencivicdata/elections/apps.py
opencivicdata/elections/admin/__init__.py
opencivicdata/elections/admin/candidacy.py
opencivicdata/elections/admin/election.py
opencivicdata/elections/admin/contests/__init__.py
opencivicdata/elections/admin/contests/ballot_measure.py
opencivicdata/elections/admin/contests/candidate.py
opencivicdata/elections/admin/contests/party.py
opencivicdata/elections/migrations/0001_initial.py
opencivicdata/elections/migrations/0002_auto_20170731_2047.py
opencivicdata/elections/migrations/0003_election_fk.py
opencivicdata/elections/migrations/0004_field_docs.py
opencivicdata/elections/migrations/0005_auto_20170823_1648.py
opencivicdata/elections/migrations/0006_auto_20171005_2029.py
opencivicdata/elections/migrations/0007_auto_20171022_0234.py
opencivicdata/elections/migrations/0008_auto_20181029_1527.py
ccdc_opencivicdata-0.0.6.dist-info/LICENSE
ccdc_opencivicdata-0.0.6.dist-info/METADATA
ccdc_opencivicdata-0.0.6.dist-info/WHEEL
ccdc_opencivicdata-0.0.6.dist-info/top_level.txt
ccdc_opencivicdata-0.0.6.dist-info/RECORD
